datadm/__init__.py
datadm/agent.py
datadm/app.py
datadm/backend.py
datadm/conversation.py
datadm/repl.py
datadm/agents/__init__.py
datadm/agents/baseline.py
datadm/agents/cotmultistep.py
datadm-0.3.6.dist-info/LICENSE
datadm-0.3.6.dist-info/METADATA
datadm-0.3.6.dist-info/WHEEL
datadm-0.3.6.dist-info/entry_points.txt
datadm-0.3.6.dist-info/top_level.txt
datadm-0.3.6.dist-info/RECORD
