Metadata-Version: 2.1
Name: datadm
Version: 0.3.6
Summary: DataDM is your private data assistant. Slide into your data's DMs
License: MIT License
Project-URL: homepage, https://github.com/approximatelabs/datadm
Keywords: nlp,ai,data,chatbot,database,csv,analytics,datachat,datadm
Classifier: Programming Language :: Python :: 3
Requires-Python: >=3.8
License-File: LICENSE
Requires-Dist: gradio
Requires-Dist: guidance ==0.0.64
Requires-Dist: jupyter
Requires-Dist: matplotlib
Requires-Dist: pandas
Requires-Dist: sketch
Requires-Dist: transformers
Requires-Dist: scikit-learn
Requires-Dist: seaborn
Requires-Dist: lxml
Requires-Dist: scipy
Requires-Dist: xgboost
Provides-Extra: all
Requires-Dist: datadm[cuda] ; extra == 'all'
Provides-Extra: cuda
Requires-Dist: accelerate ; extra == 'cuda'
